pystats19/__init__.py
pystats19/format.py
pystats19/read.py
pystats19/source.py
pystats19/utils.py
pystats19/data/pystats19_prebuilt_schema.pkl
pystats19-0.1.2.dist-info/LICENSE
pystats19-0.1.2.dist-info/METADATA
pystats19-0.1.2.dist-info/WHEEL
pystats19-0.1.2.dist-info/top_level.txt
pystats19-0.1.2.dist-info/RECORD
