Metadata-Version: 2.1
Name: pystats19
Version: 0.1.2
Summary: Python package for downloading and formatting the UK's Road Safety Data.
Author-email: Jinshuai Ma <j.ma23@lse.ac.uk>, Xiaowei Gao <ucesxwg@ucl.ac.uk>
Maintainer-email: Jinshuai Ma <j.ma23@lse.ac.uk>, Xiaowei Gao <ucesxwg@ucl.ac.uk>
License: MIT License
Project-URL: Repository, https://github.com/Mayazure/py-stats19
Requires-Python: >=3.10
License-File: LICENSE
Requires-Dist: pandas >=1.5.0
Requires-Dist: geopandas >=0.12.0
Requires-Dist: shapely >=1.8.5
Requires-Dist: numpy <2.0.0
